MANIFEST.in
README.rst
setup.py
neobolt/__init__.py
neobolt/__main__.py
neobolt/addressing.py
neobolt/diagnostics.py
neobolt/direct.py
neobolt/exceptions.py
neobolt/meta.py
neobolt/routing.py
neobolt/security.py
neobolt/versioning.py
neobolt.egg-info/PKG-INFO
neobolt.egg-info/SOURCES.txt
neobolt.egg-info/dependency_links.txt
neobolt.egg-info/top_level.txt
neobolt/bolt/__init__.py
neobolt/bolt/_io.c
neobolt/bolt/_io.pyx
neobolt/bolt/io.py
neobolt/compat/__init__.py
neobolt/compat/collections.py
neobolt/compat/ssl.py
neobolt/packstream/__init__.py
neobolt/packstream/_packer.c
neobolt/packstream/_packer.pyx
neobolt/packstream/_unpacker.c
neobolt/packstream/_unpacker.pyx
neobolt/packstream/packer.py
neobolt/packstream/unpacker.py